Binary_mul_uni/Binary_mul_5_1_uni/multi_components.v
module MHA (Sum, Cout, A, B, Sin);

   input A;
   input B;
   input Sin;

   output Sum;
   output Cout;

	wire	w1;

	and	a0(w1, A, B);

	xor	x1(Sum, w1, Sin);

	and	a1(Cout, w1, Sin);

endmodule // MHA

module MFA (Sum, Cout, A, B, Sin, Cin);

   input A;
   input B;
   input Sin;
   input Cin;   

   output Sum;
   output Cout;

	wire    w0;
	wire	w1;
	wire	w2;
	wire	w3;
	wire	w4;

	and     a1(w0, A, B);

	xor	x1(w1, w0, Sin);
	xor	x2(Sum, w1, Cin);

	nand    n1(w2, w0, Sin);
	nand    n2(w3, w0, Cin);
	nand	n3(w4, Sin, Cin);
	nand	n4(Cout, w2, w3, w4);
   // Cout=(A∧B∧Sin)∨(A∧B∧Cin)∨(Sin∧Cin)

endmodule // MFA

module FA (Sum, Cout, A, B, Cin);

   input A;
   input B;
   input Cin;   

   output Sum;
   output Cout;

	wire	w1;
	wire	w2;
	wire	w3;
	wire	w4;

	xor	x1(w1, A, B);
	xor	x2(Sum, w1, Cin);

   //Sum = A ⊕ B ⊕ Cin

	nand    n1(w2, A, B);
	nand    n2(w3, A, Cin);
	nand	n3(w4, B, Cin);
	nand	n4(Cout, w2, w3, w4);
   //Cout = (A & B) | (A & Cin) | (B & Cin)

endmodule // FA

Binary_mul_uni/Binary_mul_5_1_uni/Binary_mul_5_1_uni.v
module Binary_mul_5_1_uni (P, A, B, clk, rst_n, en);

   input unsigned [4:0] A; // 被乘数
   input unsigned [4:0] B; // 乘数    
   input clk, rst_n, en;         

   output reg unsigned [9:0] P; // 积
   wire unsigned [9:0] product_comb;

//row b0
   wire  wa10,wa20,wa30,wa40,wa50,wa60,wa70,wa80,wa90;

//row b1
   wire  wmhc01,wmhc11,wmhc21,wmhc31,wmhc41,wmhc51,wmhc61,wmhc71,wmhc81;
   wire  wmhs11,wmhs21,wmhs31,wmhs41,wmhs51,wmhs61,wmhs71,wmhs81;

//row b2
   wire	wmfc02,wmfc12,wmfc22,wmfc32,wmfc42,wmfc52,wmfc62, wmfc72;
   wire	wmfs12,wmfs22,wmfs32,wmfs42,wmfs52,wmfs62,wmfs72;

//row b3
   wire	wmfc03,wmfc13,wmfc23,wmfc33,wmfc43,wmfc53,wmfc63;
   wire	wmfs13,wmfs23,wmfs33,wmfs43,wmfs53,wmfs63;

//row b4
   wire	wfac05,wfac15,wfac25,wfac35,wfac45;


//Row bo Implementation
   and a00(product_comb[0], A[0], B[0]);
   and a10(wa10 ,A[1], B[0]);
   and a20(wa20 ,A[2], B[0]);
   and a30(wa30, A[3], B[0]);
   and a40(wa40, A[4], B[0]);
   assign wa50 = 0;
   assign wa60 = 0;
   assign wa70 = 0;
   assign wa80 = 0;
   assign wa90 = 0;

//Row b1
   MHA     mha01(.Sum(product_comb[1]), .Cout(wmhc01), .A(A[0]), .B(B[1]), .Sin(wa10));
   MHA     mha11(.Sum(wmhs11), .Cout(wmhc11), .A(A[1]), .B(B[1]), .Sin(wa20));
   MHA     mha21(.Sum(wmhs21), .Cout(wmhc21), .A(A[2]), .B(B[1]), .Sin(wa30));
   MHA     mha31(.Sum(wmhs31), .Cout(wmhc31), .A(A[3]), .B(B[1]), .Sin(wa40));
   MHA     mha41(.Sum(wmhs41), .Cout(wmhc41), .A(A[4]), .B(B[1]), .Sin(wa50));
   // assign
   MHA     mha51(.Sum(wmhs51), .Cout(wmhc51), .A(1'b0), .B(B[1]), .Sin(wa60));
   MHA     mha61(.Sum(wmhs61), .Cout(wmhc61), .A(1'b0), .B(B[1]), .Sin(wa70));
   MHA     mha71(.Sum(wmhs71), .Cout(wmhc71), .A(1'b0), .B(B[1]), .Sin(wa80));
   MHA     mha81(.Sum(wmhs81), .Cout(wmhc81), .A(1'b0), .B(B[1]), .Sin(wa90));

//Row b2
   MFA 	  mfa02(.Sum(product_comb[2]), .Cout(wmfc02), .A(A[0]), .B(B[2]), .Sin(wmhs11), .Cin(wmhc01));
   MFA 	  mfa12(.Sum(wmfs12), .Cout(wmfc12), .A(A[1]), .B(B[2]), .Sin(wmhs21), .Cin(wmhc11));
   MFA 	  mfa22(.Sum(wmfs22), .Cout(wmfc22), .A(A[2]), .B(B[2]), .Sin(wmhs31), .Cin(wmhc21));
   MFA 	  mfa32(.Sum(wmfs32), .Cout(wmfc32), .A(A[3]), .B(B[2]), .Sin(wmhs41), .Cin(wmhc31));
   MFA 	  mfa42(.Sum(wmfs42), .Cout(wmfc42), .A(A[4]), .B(B[2]), .Sin(wmhs51), .Cin(wmhc41));

   MFA 	  mfa52(.Sum(wmfs52), .Cout(wmfc52), .A(1'b0), .B(B[2]), .Sin(wmhs61), .Cin(wmhc51));
   MFA 	  mfa62(.Sum(wmfs62), .Cout(wmfc62), .A(1'b0), .B(B[2]), .Sin(wmhs71), .Cin(wmhc61));
   MFA 	  mfa72(.Sum(wmfs72), .Cout(wmfc72), .A(1'b0), .B(B[2]), .Sin(wmhs81), .Cin(wmhc71));

//Row b3
   MFA 	  mfa03(.Sum(product_comb[3]), .Cout(wmfc03), .A(A[0]), .B(B[3]), .Sin(wmfs12), .Cin(wmfc02));
   MFA 	  mfa13(.Sum(wmfs13), .Cout(wmfc13), .A(A[1]), .B(B[3]), .Sin(wmfs22), .Cin(wmfc12));
   MFA 	  mfa23(.Sum(wmfs23), .Cout(wmfc23), .A(A[2]), .B(B[3]), .Sin(wmfs32), .Cin(wmfc22));
   MFA 	  mfa33(.Sum(wmfs33), .Cout(wmfc33), .A(A[3]), .B(B[3]), .Sin(wmfs42), .Cin(wmfc32));
   MFA 	  mfa43(.Sum(wmfs43), .Cout(wmfc43), .A(A[4]), .B(B[3]), .Sin(wmfs52), .Cin(wmfc42));

   MFA 	  mfa53(.Sum(wmfs53), .Cout(wmfc53), .A(1'b0), .B(B[3]), .Sin(wmfs62), .Cin(wmfc52));
   MFA 	  mfa63(.Sum(wmfs63), .Cout(wmfc63), .A(1'b0), .B(B[3]), .Sin(wmfs72), .Cin(wmfc62));
   
//Row b4
   MFA 	  mfa04(.Sum(product_comb[4]), .Cout(wmfc04), .A(A[0]), .B(B[4]), .Sin(wmfs13), .Cin(wmfc03));
   MFA 	  mfa14(.Sum(wmfs14), .Cout(wmfc14), .A(A[1]), .B(B[4]), .Sin(wmfs23), .Cin(wmfc13));
   MFA 	  mfa24(.Sum(wmfs24), .Cout(wmfc24), .A(A[2]), .B(B[4]), .Sin(wmfs33), .Cin(wmfc23));
   MFA 	  mfa34(.Sum(wmfs34), .Cout(wmfc34), .A(A[3]), .B(B[4]), .Sin(wmfs43), .Cin(wmfc33));
   MFA 	  mfa44(.Sum(wmfs44), .Cout(wmfc44), .A(a[4]), .B(B[4]), .Sin(wmfs53), .Cin(wmfc43));

   MFA     mfa54(.Sum(wmfs54), .Cout(wmfc54), .A(1'b0), .B(B[4]), .Sin(wmfs63), .Cin(wmfc53));

//Row b5
   FA 	  fa05(.Sum(product_comb[5]), .Cout(wfac05), .A(wmfc04), .B(wmfs14), .Cin(1'b0));
   FA 	  fa15(.Sum(product_comb[6]), .Cout(wfac15), .A(wmfc14), .B(wmfs24), .Cin(wfac05));
   FA 	  fa25(.Sum(product_comb[7]), .Cout(wfac25), .A(wmfc24), .B(wmfs34), .Cin(wfac15));
   FA 	  fa35(.Sum(product_comb[8]), .Cout(wfac35), .A(wmfc34), .B(wmfs44), .Cin(wfac25));
   FA 	  fa45(.Sum(product_comb[9]), .Cout(wfac45), .A(wmfc44), .B(wmfs54), .Cin(wfac35));


   always @(posedge clk or negedge rst_n) begin
      if (!rst_n)
         P <= 10'd0;
      else if (en)
         P <= product_comb;
      else 
         P <= P;
   end

endmodule

Binary_mul_uni/Binary_mul_5_1_uni/Binary_mul_5_1_uni_tb.v
module Binary_mul_5_1_uni_tb();

    reg unsigned [4:0] A;
    reg unsigned [4:0] B;
    reg clk;
    reg rst_n;
    reg en;

    wire unsigned [9:0] P;

    integer i, j;
    reg [9:0] expected_P;

    Binary_mul_5_1_uni uut (
        .A(A),
        .B(B),
        .P(P),
        .clk(clk),
        .rst_n(rst_n),
        .en(en)
    );

    initial begin
        clk = 0;
        forever #5 clk = ~clk; 
    end

    initial begin
        $dumpfile("wave.vcd"); 
        $dumpvars(0, Binary_mul_5_1_uni_tb); 

        rst_n = 0;
        en = 0;
        A = 0;
        B = 0;

        // Apply reset
        #10;
        rst_n = 1;
        en = 1;

        for (i = 0; i < 32; i = i + 1) begin
            for (j = 0; j < 16; j = j + 1) begin
                @(negedge clk);
                A = i;
                B = j;
                expected_P = i * j; 
                #1;
                @(posedge clk);
                #1;  

                if (P !== expected_P) begin
                    $display("ERROR: A=%d, B=%d, Expected P=%d, Actual P=%d", A, B, expected_P, P);
                end else begin
                    $display("PASS:  A=%d, B=%d, P=%d", A, B, P);
                end
            end
        end

        $finish;  // End the simulation
    end

endmodule

Binary_mul_uni/Binary_mul_5_1_uni/wave.vcd
$date
	Sun Oct 13 17:41:29 2024
$end
$version
	Icarus Verilog
$end
$timescale
	1s
$end
$scope module Binary_mul_5_1_uni_tb $end
$var wire 10 ! P [9:0] $end
$var reg 5 " A [4:0] $end
$var reg 5 # B [4:0] $end
$var reg 1 $ clk $end
$var reg 1 % en $end
$var reg 10 & expected_P [9:0] $end
$var reg 1 ' rst_n $end
$var integer 32 ( i [31:0] $end
$var integer 32 ) j [31:0] $end
$scope module uut $end
$var wire 5 * A [4:0] $end
$var wire 5 + B [4:0] $end
$var wire 1 $ clk $end
$var wire 1 % en $end
$var wire 1 ' rst_n $end
$var wire 1 , wa10 $end
$var wire 1 - wa20 $end
$var wire 1 . wa30 $end
$var wire 1 / wa40 $end
$var wire 1 0 wa50 $end
$var wire 1 1 wa60 $end
$var wire 1 2 wa70 $end
$var wire 1 3 wa80 $end
$var wire 1 4 wa90 $end
$var wire 1 5 wmhs81 $end
$var wire 1 6 wmhs71 $end
$var wire 1 7 wmhs61 $end
$var wire 1 8 wmhs51 $end
$var wire 1 9 wmhs41 $end
$var wire 1 : wmhs31 $end
$var wire 1 ; wmhs21 $end
$var wire 1 < wmhs11 $end
$var wire 1 = wmhc81 $end
$var wire 1 > wmhc71 $end
$var wire 1 ? wmhc61 $end
$var wire 1 @ wmhc51 $end
$var wire 1 A wmhc41 $end
$var wire 1 B wmhc31 $end
$var wire 1 C wmhc21 $end
$var wire 1 D wmhc11 $end
$var wire 1 E wmhc01 $end
$var wire 1 F wmfs72 $end
$var wire 1 G wmfs63 $end
$var wire 1 H wmfs62 $end
$var wire 1 I wmfs54 $end
$var wire 1 J wmfs53 $end
$var wire 1 K wmfs52 $end
$var wire 1 L wmfs44 $end
$var wire 1 M wmfs43 $end
$var wire 1 N wmfs42 $end
$var wire 1 O wmfs34 $end
$var wire 1 P wmfs33 $end
$var wire 1 Q wmfs32 $end
$var wire 1 R wmfs24 $end
$var wire 1 S wmfs23 $end
$var wire 1 T wmfs22 $end
$var wire 1 U wmfs14 $end
$var wire 1 V wmfs13 $end
$var wire 1 W wmfs12 $end
$var wire 1 X wmfc72 $end
$var wire 1 Y wmfc63 $end
$var wire 1 Z wmfc62 $end
$var wire 1 [ wmfc54 $end
$var wire 1 \ wmfc53 $end
$var wire 1 ] wmfc52 $end
$var wire 1 ^ wmfc44 $end
$var wire 1 _ wmfc43 $end
$var wire 1 ` wmfc42 $end
$var wire 1 a wmfc34 $end
$var wire 1 b wmfc33 $end
$var wire 1 c wmfc32 $end
$var wire 1 d wmfc24 $end
$var wire 1 e wmfc23 $end
$var wire 1 f wmfc22 $end
$var wire 1 g wmfc14 $end
$var wire 1 h wmfc13 $end
$var wire 1 i wmfc12 $end
$var wire 1 j wmfc04 $end
$var wire 1 k wmfc03 $end
$var wire 1 l wmfc02 $end
$var wire 1 m wfac45 $end
$var wire 1 n wfac35 $end
$var wire 1 o wfac25 $end
$var wire 1 p wfac15 $end
$var wire 1 q wfac05 $end
$var wire 10 r product_comb [9:0] $end
$var reg 10 s P [9:0] $end
$scope module fa05 $end
$var wire 1 t Cin $end
$var wire 1 q Cout $end
$var wire 1 u Sum $end
$var wire 1 v w1 $end
$var wire 1 w w2 $end
$var wire 1 x w3 $end
$var wire 1 y w4 $end
$var wire 1 U B $end
$var wire 1 j A $end
$upscope $end
$scope module fa15 $end
$var wire 1 q Cin $end
$var wire 1 p Cout $end
$var wire 1 z Sum $end
$var wire 1 { w1 $end
$var wire 1 | w2 $end
$var wire 1 } w3 $end
$var wire 1 ~ w4 $end
$var wire 1 R B $end
$var wire 1 g A $end
$upscope $end
$scope module fa25 $end
$var wire 1 p Cin $end
$var wire 1 o Cout $end
$var wire 1 !" Sum $end
$var wire 1 "" w1 $end
$var wire 1 #" w2 $end
$var wire 1 $" w3 $end
$var wire 1 %" w4 $end
$var wire 1 O B $end
$var wire 1 d A $end
$upscope $end
$scope module fa35 $end
$var wire 1 o Cin $end
$var wire 1 n Cout $end
$var wire 1 &" Sum $end
$var wire 1 '" w1 $end
$var wire 1 (" w2 $end
$var wire 1 )" w3 $end
$var wire 1 *" w4 $end
$var wire 1 L B $end
$var wire 1 a A $end
$upscope $end
$scope module fa45 $end
$var wire 1 n Cin $end
$var wire 1 m Cout $end
$var wire 1 +" Sum $end
$var wire 1 ," w1 $end
$var wire 1 -" w2 $end
$var wire 1 ." w3 $end
$var wire 1 /" w4 $end
$var wire 1 I B $end
$var wire 1 ^ A $end
$upscope $end
$scope module mfa02 $end
$var wire 1 0" A $end
$var wire 1 1" B $end
$var wire 1 l Cout $end
$var wire 1 2" Sum $end
$var wire 1 3" w0 $end
$var wire 1 4" w1 $end
$var wire 1 5" w2 $end
$var wire 1 6" w3 $end
$var wire 1 7" w4 $end
$var wire 1 < Sin $end
$var wire 1 E Cin $end
$upscope $end
$scope module mfa03 $end
$var wire 1 8" A $end
$var wire 1 9" B $end
$var wire 1 l Cin $end
$var wire 1 k Cout $end
$var wire 1 :" Sum $end
$var wire 1 ;" w0 $end
$var wire 1 <" w1 $end
$var wire 1 =" w2 $end
$var wire 1 >" w3 $end
$var wire 1 ?" w4 $end
$var wire 1 W Sin $end
$upscope $end
$scope module mfa04 $end
$var wire 1 @" A $end
$var wire 1 A" B $end
$var wire 1 k Cin $end
$var wire 1 j Cout $end
$var wire 1 B" Sum $end
$var wire 1 C" w0 $end
$var wire 1 D" w1 $end
$var wire 1 E" w2 $end
$var wire 1 F" w3 $end
$var wire 1 G" w4 $end
$var wire 1 V Sin $end
$upscope $end
$scope module mfa12 $end
$var wire 1 H" A $end
$var wire 1 I" B $end
$var wire 1 i Cout $end
$var wire 1 W Sum $end
$var wire 1 J" w0 $end
$var wire 1 K" w1 $end
$var wire 1 L" w2 $end
$var wire 1 M" w3 $end
$var wire 1 N" w4 $end
$var wire 1 ; Sin $end
$var wire 1 D Cin $end
$upscope $end
$scope module mfa13 $end
$var wire 1 O" A $end
$var wire 1 P" B $end
$var wire 1 i Cin $end
$var wire 1 h Cout $end
$var wire 1 V Sum $end
$var wire 1 Q" w0 $end
$var wire 1 R" w1 $end
$var wire 1 S" w2 $end
$var wire 1 T" w3 $end
$var wire 1 U" w4 $end
$var wire 1 T Sin $end
$upscope $end
$scope module mfa14 $end
$var wire 1 V" A $end
$var wire 1 W" B $end
$var wire 1 h Cin $end
$var wire 1 g Cout $end
$var wire 1 U Sum $end
$var wire 1 X" w0 $end
$var wire 1 Y" w1 $end
$var wire 1 Z" w2 $end
$var wire 1 [" w3 $end
$var wire 1 \" w4 $end
$var wire 1 S Sin $end
$upscope $end
$scope module mfa22 $end
$var wire 1 ]" A $end
$var wire 1 ^" B $end
$var wire 1 f Cout $end
$var wire 1 T Sum $end
$var wire 1 _" w0 $end
$var wire 1 `" w1 $end
$var wire 1 a" w2 $end
$var wire 1 b" w3 $end
$var wire 1 c" w4 $end
$var wire 1 : Sin $end
$var wire 1 C Cin $end
$upscope $end
$scope module mfa23 $end
$var wire 1 d" A $end
$var wire 1 e" B $end
$var wire 1 f Cin $end
$var wire 1 e Cout $end
$var wire 1 S Sum $end
$var wire 1 f" w0 $end
$var wire 1 g" w1 $end
$var wire 1 h" w2 $end
$var wire 1 i" w3 $end
$var wire 1 j" w4 $end
$var wire 1 Q Sin $end
$upscope $end
$scope module mfa24 $end
$var wire 1 k" A $end
$var wire 1 l" B $end
$var wire 1 e Cin $end
$var wire 1 d Cout $end
$var wire 1 R Sum $end
$var wire 1 m" w0 $end
$var wire 1 n" w1 $end
$var wire 1 o" w2 $end
$var wire 1 p" w3 $end
$var wire 1 q" w4 $end
$var wire 1 P Sin $end
$upscope $end
$scope module mfa32 $end
$var wire 1 r" A $end
$var wire 1 s" B $end
$var wire 1 c Cout $end
$var wire 1 Q Sum $end
$var wire 1 t" w0 $end
$var wire 1 u" w1 $end
$var wire 1 v" w2 $end
$var wire 1 w" w3 $end
$var wire 1 x" w4 $end
$var wire 1 9 Sin $end
$var wire 1 B Cin $end
$upscope $end
$scope module mfa33 $end
$var wire 1 y" A $end
$var wire 1 z" B $end
$var wire 1 c Cin $end
$var wire 1 b Cout $end
$var wire 1 P Sum $end
$var wire 1 {" w0 $end
$var wire 1 |" w1 $end
$var wire 1 }" w2 $end
$var wire 1 ~" w3 $end
$var wire 1 !# w4 $end
$var wire 1 N Sin $end
$upscope $end
$scope module mfa34 $end
$var wire 1 "# A $end
$var wire 1 ## B $end
$var wire 1 b Cin $end
$var wire 1 a Cout $end
$var wire 1 O Sum $end
$var wire 1 $# w0 $end
$var wire 1 %# w1 $end
$var wire 1 &# w2 $end
$var wire 1 '# w3 $end
$var wire 1 (# w4 $end
$var wire 1 M Sin $end
$upscope $end
$scope module mfa42 $end
$var wire 1 )# A $end
$var wire 1 *# B $end
$var wire 1 ` Cout $end
$var wire 1 N Sum $end
$var wire 1 +# w0 $end
$var wire 1 ,# w1 $end
$var wire 1 -# w2 $end
$var wire 1 .# w3 $end
$var wire 1 /# w4 $end
$var wire 1 8 Sin $end
$var wire 1 A Cin $end
$upscope $end
$scope module mfa43 $end
$var wire 1 0# A $end
$var wire 1 1# B $end
$var wire 1 ` Cin $end
$var wire 1 _ Cout $end
$var wire 1 M Sum $end
$var wire 1 2# w0 $end
$var wire 1 3# w1 $end
$var wire 1 4# w2 $end
$var wire 1 5# w3 $end
$var wire 1 6# w4 $end
$var wire 1 K Sin $end
$upscope $end
$scope module mfa44 $end
$var wire 1 7# A $end
$var wire 1 8# B $end
$var wire 1 _ Cin $end
$var wire 1 ^ Cout $end
$var wire 1 L Sum $end
$var wire 1 9# w0 $end
$var wire 1 :# w1 $end
$var wire 1 ;# w2 $end
$var wire 1 <# w3 $end
$var wire 1 =# w4 $end
$var wire 1 J Sin $end
$upscope $end
$scope module mfa52 $end
$var wire 1 ># A $end
$var wire 1 ?# B $end
$var wire 1 ] Cout $end
$var wire 1 K Sum $end
$var wire 1 @# w0 $end
$var wire 1 A# w1 $end
$var wire 1 B# w2 $end
$var wire 1 C# w3 $end
$var wire 1 D# w4 $end
$var wire 1 7 Sin $end
$var wire 1 @ Cin $end
$upscope $end
$scope module mfa53 $end
$var wire 1 E# A $end
$var wire 1 F# B $end
$var wire 1 ] Cin $end
$var wire 1 \ Cout $end
$var wire 1 J Sum $end
$var wire 1 G# w0 $end
$var wire 1 H# w1 $end
$var wire 1 I# w2 $end
$var wire 1 J# w3 $end
$var wire 1 K# w4 $end
$var wire 1 H Sin $end
$upscope $end
$scope module mfa54 $end
$var wire 1 L# A $end
$var wire 1 M# B $end
$var wire 1 \ Cin $end
$var wire 1 [ Cout $end
$var wire 1 I Sum $end
$var wire 1 N# w0 $end
$var wire 1 O# w1 $end
$var wire 1 P# w2 $end
$var wire 1 Q# w3 $end
$var wire 1 R# w4 $end
$var wire 1 G Sin $end
$upscope $end
$scope module mfa62 $end
$var wire 1 S# A $end
$var wire 1 T# B $end
$var wire 1 Z Cout $end
$var wire 1 H Sum $end
$var wire 1 U# w0 $end
$var wire 1 V# w1 $end
$var wire 1 W# w2 $end
$var wire 1 X# w3 $end
$var wire 1 Y# w4 $end
$var wire 1 6 Sin $end
$var wire 1 ? Cin $end
$upscope $end
$scope module mfa63 $end
$var wire 1 Z# A $end
$var wire 1 [# B $end
$var wire 1 Z Cin $end
$var wire 1 Y Cout $end
$var wire 1 G Sum $end
$var wire 1 \# w0 $end
$var wire 1 ]# w1 $end
$var wire 1 ^# w2 $end
$var wire 1 _# w3 $end
$var wire 1 `# w4 $end
$var wire 1 F Sin $end
$upscope $end
$scope module mfa72 $end
$var wire 1 a# A $end
$var wire 1 b# B $end
$var wire 1 X Cout $end
$var wire 1 F Sum $end
$var wire 1 c# w0 $end
$var wire 1 d# w1 $end
$var wire 1 e# w2 $end
$var wire 1 f# w3 $end
$var wire 1 g# w4 $end
$var wire 1 5 Sin $end
$var wire 1 > Cin $end
$upscope $end
$scope module mha01 $end
$var wire 1 h# A $end
$var wire 1 i# B $end
$var wire 1 E Cout $end
$var wire 1 , Sin $end
$var wire 1 j# Sum $end
$var wire 1 k# w1 $end
$upscope $end
$scope module mha11 $end
$var wire 1 l# A $end
$var wire 1 m# B $end
$var wire 1 D Cout $end
$var wire 1 - Sin $end
$var wire 1 < Sum $end
$var wire 1 n# w1 $end
$upscope $end
$scope module mha21 $end
$var wire 1 o# A $end
$var wire 1 p# B $end
$var wire 1 C Cout $end
$var wire 1 . Sin $end
$var wire 1 ; Sum $end
$var wire 1 q# w1 $end
$upscope $end
$scope module mha31 $end
$var wire 1 r# A $end
$var wire 1 s# B $end
$var wire 1 B Cout $end
$var wire 1 / Sin $end
$var wire 1 : Sum $end
$var wire 1 t# w1 $end
$upscope $end
$scope module mha41 $end
$var wire 1 u# A $end
$var wire 1 v# B $end
$var wire 1 A Cout $end
$var wire 1 0 Sin $end
$var wire 1 9 Sum $end
$var wire 1 w# w1 $end
$upscope $end
$scope module mha51 $end
$var wire 1 x# A $end
$var wire 1 y# B $end
$var wire 1 @ Cout $end
$var wire 1 1 Sin $end
$var wire 1 8 Sum $end
$var wire 1 z# w1 $end
$upscope $end
$scope module mha61 $end
$var wire 1 {# A $end
$var wire 1 |# B $end
$var wire 1 ? Cout $end
$var wire 1 2 Sin $end
$var wire 1 7 Sum $end
$var wire 1 }# w1 $end
$upscope $end
$scope module mha71 $end
$var wire 1 ~# A $end
$var wire 1 !$ B $end
$var wire 1 > Cout $end
$var wire 1 3 Sin $end
$var wire 1 6 Sum $end
$var wire 1 "$ w1 $end
$upscope $end
$scope module mha81 $end
$var wire 1 #$ A $end
$var wire 1 $$ B $end
$var wire 1 = Cout $end
$var wire 1 4 Sin $end
$var wire 1 5 Sum $end
$var wire 1 %$ w1 $end
$upscope $end
$upscope $end
$upscope $end
$enddefinitions $end
#0
$dumpvars
0%$
0$$
0#$
0"$
0!$
0~#
0}#
0|#
0{#
0z#
0y#
0x#
0w#
0v#
0u#
0t#
0s#
0r#
0q#
0p#
0o#
0n#
0m#
0l#
0k#
0j#
0i#
0h#
1g#
1f#
1e#
0d#
0c#
0b#
0a#
1`#
1_#
1^#
0]#
0\#
0[#
0Z#
1Y#
1X#
1W#
0V#
0U#
0T#
0S#
1R#
1Q#
1P#
0O#
0N#
0M#
0L#
1K#
1J#
1I#
0H#
0G#
0F#
0E#
1D#
1C#
1B#
0A#
0@#
0?#
0>#
1=#
1<#
1;#
0:#
09#
08#
07#
16#
15#
14#
03#
02#
01#
00#
1/#
1.#
1-#
0,#
0+#
0*#
0)#
1(#
1'#
1&#
0%#
0$#
0##
0"#
1!#
1~"
1}"
0|"
0{"
0z"
0y"
1x"
1w"
1v"
0u"
0t"
0s"
0r"
1q"
1p"
1o"
0n"
0m"
0l"
0k"
1j"
1i"
1h"
0g"
0f"
0e"
0d"
1c"
1b"
1a"
0`"
0_"
0^"
0]"
1\"
1["
1Z"
0Y"
0X"
0W"
0V"
1U"
1T"
1S"
0R"
0Q"
0P"
0O"
1N"
1M"
1L"
0K"
0J"
0I"
0H"
1G"
1F"
1E"
0D"
0C"
0B"
0A"
0@"
1?"
1>"
1="
0<"
0;"
0:"
09"
08"
17"
16"
15"
04"
03"
02"
01"
00"
1/"
1."
1-"
0,"
0+"
1*"
1)"
1("
0'"
0&"
1%"
1$"
1#"
0""
0!"
1~
1}
1|
0{
0z
1y
1x
1w
0v
0u
0t
b0 s
b0 r
0q
0p
0o
0n
0m
0l
0k
0j
0i
0h
0g
0f
0e
0d
0c
0b
0a
0`
0_
0^
0]
0\
0[
0Z
0Y
0X
0W
0V
0U
0T
0S
0R
0Q
0P
0O
0N
0M
0L
0K
0J
0I
0H
0G
0F
0E
0D
0C
0B
0A
0@
0?
0>
0=
0<
0;
0:
09
08
07
06
05
04
03
02
01
00
0/
0.
0-
0,
b0 +
b0 *
bx )
bx (
0'
bx &
0%
0$
b0 #
b0 "
b0 !
$end
#5
1$
#10
b0 &
0$
b0 )
b0 (
1%
1'
#15
1$
#16
b1 )
#20
b1 #
b1 +
0$
#25
1$
#26
b10 )
#30
1i#
1m#
1p#
1s#
1v#
1y#
1|#
1!$
1$$
b10 #
b10 +
0$
#35
1$
#36
b11 )
#40
b11 #
b11 +
0$
#45
1$
#46
b100 )
#50
0i#
0m#
0p#
0s#
0v#
0y#
0|#
0!$
0$$
11"
1I"
1^"
1s"
1*#
1?#
1T#
1b#
b100 #
b100 +
0$
#55
1$
#56
b101 )
#60
b101 #
b101 +
0$
#65
1$
#66
b110 )
#70
1i#
1m#
1p#
1s#
1v#
1y#
1|#
1!$
1$$
b110 #
b110 +
0$
#75
1$
#76
b111 )
#80
b111 #
b111 +
0$
#85
1$
#86
b1000 )
#90
0i#
0m#
0p#
0s#
0v#
0y#
0|#
0!$
0$$
01"
0I"
0^"
0s"
0*#
0?#
0T#
0b#
19"
1P"
1e"
1z"
11#
1F#
1[#
b1000 #
b1000 +
0$
#95
1$
#96
b1001 )
#100
b1001 #
b1001 +
0$
#105
1$
#106
b1010 )
#110
1i#
1m#
1p#
1s#
1v#
1y#
1|#
1!$
1$$
b1010 #
b1010 +
0$
#115
1$
#116
b1011 )
#120
b1011 #
b1011 +
0$
#125
1$
#126
b1100 )
#130
0i#
0m#
0p#
0s#
0v#
0y#
0|#
0!$
0$$
11"
1I"
1^"
1s"
1*#
1?#
1T#
1b#
b1100 #
b1100 +
0$
#135
1$
#136
b1101 )
#140
b1101 #
b1101 +
0$
#145
1$
#146
b1110 )
#150
1i#
1m#
1p#
1s#
1v#
1y#
1|#
1!$
1$$
b1110 #
b1110 +
0$
#155
1$
#156
b1111 )
#160
b1111 #
b1111 +
0$
#165
1$
#166
b10000 )
#170
0i#
0m#
0p#
0s#
0v#
0y#
0|#
0!$
0$$
01"
0I"
0^"
0s"
0*#
0?#
0T#
0b#
09"
0P"
0e"
0z"
01#
0F#
0[#
1A"
1W"
1l"
1##
18#
1M#
b10000 #
b10000 +
0$
#175
1$
#176
b10001 )
#180
b10001 #
b10001 +
0$
#185
1$
#186
b10010 )
#190
1i#
1m#
1p#
1s#
1v#
1y#
1|#
1!$
1$$
b10010 #
b10010 +
0$
#195
1$
#196
b10011 )
#200
b10011 #
b10011 +
0$
#205
1$
#206
b10100 )
#210
0i#
0m#
0p#
0s#
0v#
0y#
0|#
0!$
0$$
11"
1I"
1^"
1s"
1*#
1?#
1T#
1b#
b10100 #
b10100 +
0$
#215
1$
#216
b10101 )
#220
b10101 #
b10101 +
0$
#225
1$
#226
b10110 )
#230
1i#
1m#
1p#
1s#
1v#
1y#
1|#
1!$
1$$
b10110 #
b10110 +
0$
#235
1$
#236
b10111 )
#240
b10111 #
b10111 +
0$
#245
1$
#246
b11000 )
#250
0i#
0m#
0p#
0s#
0v#
0y#
0|#
0!$
0$$
01"
0I"
0^"
0s"
0*#
0?#
0T#
0b#
19"
1P"
1e"
1z"
11#
1F#
1[#
b11000 #
b11000 +
0$
#255
1$
#256
b11001 )
#260
b11001 #
b11001 +
0$
#265
1$
#266
b11010 )
#270
1i#
1m#
1p#
1s#
1v#
1y#
1|#
1!$
1$$
b11010 #
b11010 +
0$
#275
1$
#276
b11011 )
#280
b11011 #
b11011 +
0$
#285
1$
#286
b11100 )
#290
0i#
0m#
0p#
0s#
0v#
0y#
0|#
0!$
0$$
11"
1I"
1^"
1s"
1*#
1?#
1T#
1b#
b11100 #
b11100 +
0$
#295
1$
#296
b11101 )
#300
b11101 #
b11101 +
0$
#305
1$
#306
b11110 )
#310
1i#
1m#
1p#
1s#
1v#
1y#
1|#
1!$
1$$
b11110 #
b11110 +
0$
#315
1$
#316
b11111 )
#320
b11111 #
b11111 +
0$
#325
1$
#326
b1 (
b0 )
#330
0i#
0m#
0p#
0s#
0v#
0y#
0|#
0!$
0$$
01"
0I"
0^"
0s"
0*#
0?#
0T#
0b#
09"
0P"
0e"
0z"
01#
0F#
0[#
0A"
0W"
0l"
0##
08#
0M#
1h#
10"
18"
1@"
b0 #
b0 +
b1 "
b1 *
0$
#335
1$
#336
b1 )
#340
b1 r
b1 &
b1 #
b1 +
0$
#345
b1 !
b1 s
1$
#346
b10 )
#350
1j#
b10 r
1k#
1i#
1m#
1p#
1s#
1v#
1y#
1|#
1!$
1$$
b10 &
b10 #
b10 +
0$
#355
b10 !
b10 s
1$
#356
b11 )
#360
b11 r
b11 &
b11 #
b11 +
0$
#365
b11 !
b11 s
1$
#366
b100 )
#370
12"
0j#
14"
b100 r
0k#
13"
0i#
0m#
0p#
0s#
0v#
0y#
0|#
0!$
0$$
11"
1I"
1^"
1s"
1*#
1?#
1T#
1b#
b100 &
b100 #
b100 +
0$
#375
b100 !
b100 s
1$
#376
b101 )
#380
b101 r
b101 &
b101 #
b101 +
0$
#385
b101 !
b101 s
1$
#386
b110 )
